LICENSE
MANIFEST.in
README.rst
requirements.txt
setup.cfg
setup.py
sqlquery/__init__.py
sqlquery/_querybuilder.py
sqlquery/joinbuilder.py
sqlquery/queryapi.py
sqlquery/sqlencoding.py
sqlquery.egg-info/PKG-INFO
sqlquery.egg-info/SOURCES.txt
sqlquery.egg-info/dependency_links.txt
sqlquery.egg-info/top_level.txt
sqlquery.egg-info/zip-safe